AutomateGoFiveLib/__init__.py
AutomateGoFiveLib/detect/__init__.py
AutomateGoFiveLib/detect/detectelement.py
AutomateGoFiveLib/detect/flutterfinderwidget.py
AutomateGoFiveLib/keywords/__init__.py
AutomateGoFiveLib/keywords/capturescreenshot.py
AutomateGoFiveLib/keywords/connectionmanagement.py
AutomateGoFiveLib/keywords/controlelement.py
AutomateGoFiveLib/keywords/convertobject.py
AutomateGoFiveLib/keywords/imageprocessing.py
AutomateGoFiveLib/keywords/keyevent.py
AutomateGoFiveLib/keywords/mongodbcrud.py
AutomateGoFiveLib/keywords/scroll.py
AutomateGoFiveLib/keywords/toolkitstest.py
AutomateGoFiveLib/keywords/touch.py
AutomateGoFiveLib/keywords/waitingelement.py
AutomateGoFiveLib/utils/__init__.py
AutomateGoFiveLib/utils/applicationcache.py
automategofivelib-1.0.2.dist-info/licenses/LICENSE
automategofivelib-1.0.2.dist-info/METADATA
automategofivelib-1.0.2.dist-info/WHEEL
automategofivelib-1.0.2.dist-info/top_level.txt
automategofivelib-1.0.2.dist-info/RECORD
